pwdriver/__init__.py
pwdriver/core.py
pwdriver/listener.py
pwdriver/page.py
pwdriver/util.py
pwdriver/val.py
pwdriver-0.27.3.dist-info/LICENSE
pwdriver-0.27.3.dist-info/METADATA
pwdriver-0.27.3.dist-info/WHEEL
pwdriver-0.27.3.dist-info/RECORD
