Metadata-Version: 2.1
Name: pwdriver
Version: 0.27.3
Summary: It will download a WebDriver, and then set basic configuration automatically.
Home-page: https://github.com/jinmoo21/pwdriver
License: MIT
Keywords: python,testing,automation,webdriver,selenium,test-automation,selenium-webdriver,appium,appium-webdriver
Author: Jinmoo Han
Author-email: jinmoo21@naver.com
Maintainer: Jinmoo Han
Maintainer-email: jinmoo21@naver.com
Requires-Python: >=3.7,<4.0
Classifier: License :: OSI Approved :: MIT License
Classifier: Operating System :: OS Independent
Classifier: Programming Language :: Python :: 3
Classifier: Programming Language :: Python :: 3.7
Classifier: Programming Language :: Python :: 3.8
Classifier: Programming Language :: Python :: 3.9
Classifier: Programming Language :: Python :: 3.10
Classifier: Programming Language :: Python :: 3.11
Classifier: Topic :: Software Development :: Quality Assurance
Classifier: Topic :: Software Development :: Testing
Requires-Dist: Appium-Python-Client (>=2.11.1,<3.0.0)
Requires-Dist: requests (>=2.31.0,<3.0.0)
Requires-Dist: selenium (>=4.10.0,<5.0.0)
Project-URL: Bug Reports, https://github.com/jinmoo21/pwdriver/issues
Project-URL: Repository, https://github.com/jinmoo21/pwdriver
